<?xml version="1.0" encoding="utf-8"?><toc><breadcrumbs><li><a href="N_Firefly_Box.htm">Docs</a></li><li><a href="N_Firefly_Box_Data_Storage.htm">Firefly.<wbr />Box.<wbr />Data.<wbr />Storage</a></li></breadcrumbs><tocItems><li><a id="T_Firefly_Box_Data_Storage_DateTimeDateStorage" class="has-submenu" href="T_Firefly_Box_Data_Storage_DateTimeDateStorage.htm"><span data-tocFile="../toc/IDAG.xml" class="icon toggle" onclick="ToggleExpandCollapse(this); return false;"><i class="fa fa-angle-right"> </i></span>Date<wbr />Time<wbr />Date<wbr />Storage</a><ul class="toc-menu is-hidden"> </ul></li><li><a id="T_Firefly_Box_Data_Storage_StringDateStorage" class="has-submenu" href="T_Firefly_Box_Data_Storage_StringDateStorage.htm"><span data-tocFile="../toc/IDBG.xml" class="icon toggle" onclick="ToggleExpandCollapse(this); return false;"><i class="fa fa-angle-right"> </i></span>String<wbr />Date<wbr />Storage</a><ul class="toc-menu is-hidden"> </ul></li><li><a id="T_Firefly_Box_Data_Storage_StringTextStorage" class="has-submenu" href="T_Firefly_Box_Data_Storage_StringTextStorage.htm"><span data-tocFile="../toc/IDCG.xml" class="icon toggle" onclick="ToggleExpandCollapse(this); return false;"><i class="fa fa-angle-right"> </i></span>String<wbr />Text<wbr />Storage</a><ul class="toc-menu is-hidden"> </ul></li></tocItems></toc>